syntok/__init__.py
syntok/_segmentation_states.py
syntok/segmenter.py
syntok/segmenter_test.py
syntok/tokenizer.py
syntok/tokenizer_test.py
syntok/tokenizer_test.txt
syntok-1.4.3.dist-info/LICENSE
syntok-1.4.3.dist-info/WHEEL
syntok-1.4.3.dist-info/METADATA
syntok-1.4.3.dist-info/RECORD
